dj_secrets_loader
